core_library/__init__.py
core_library/dagster/dagster_asset_check_factory.py
core_library/exceptions/__init__.py
core_library/exceptions/exceptions_repo.py
core_library/handler/__init__.py
core_library/handler/strava_api.py
core_library/utilities/__init__.py
core_library/utilities/dagster_utils.py
core_library/utilities/data_utils.py
core_library/utilities/date_utils.py
core_library/utilities/file_utils.py
core_library/utilities/misc_utils.py
core_library/utilities/polars_dataframe_utils.py
core_library/utilities/text_utils.py
gculp_data_eng_package-0.1.1.dist-info/METADATA
gculp_data_eng_package-0.1.1.dist-info/WHEEL
gculp_data_eng_package-0.1.1.dist-info/RECORD
