Metadata-Version: 2.1
Name: gculp-data-eng-package
Version: 0.1.1
Summary: Grant Culp Modern Data Stack Open Source Project
Author: Grant Culp
Author-email: culpgrant21@gmail.com
Requires-Python: >=3.11,<4.0
Classifier: Programming Language :: Python :: 3
Classifier: Programming Language :: Python :: 3.11
Classifier: Programming Language :: Python :: 3.12
Requires-Dist: dagster (>=1.5.12,<2.0.0)
Requires-Dist: dagster-duckdb (==0.22.4)
Requires-Dist: dagster-polars (>=0.3.1,<0.4.0)
Requires-Dist: dagster-slack (>=0.22.0,<0.23.0)
Requires-Dist: dagster-webserver (>=1.5.5,<2.0.0)
Requires-Dist: dbt-core (==1.7.7)
Requires-Dist: dbt-duckdb (>=1.6.2,<2.0.0)
Requires-Dist: polars[pyarrow] (==0.20.13)
Requires-Dist: pyright (>=1.1.345,<2.0.0)
Requires-Dist: pytest (>=8.0.0,<9.0.0)
Requires-Dist: sphinx (==7.2.6)
Requires-Dist: tenacity (>=8.2.3,<9.0.0)
